<system>
    <partition id="0" proc="12" maj_fr="10000">
        <task id="25" prio="25" bcet="4" wcet="84" period="10000" deadline="10000"/>
        <task id="24" prio="24" bcet="1" wcet="28" period="10000" deadline="10000"/>
        <task id="28" prio="28" bcet="2" wcet="54" period="10000" deadline="10000"/>
        <task id="35" prio="35" bcet="2" wcet="52" period="10000" deadline="10000"/>
        <task id="37" prio="37" bcet="0" wcet="6" period="10000" deadline="10000"/>
        <task id="46" prio="46" bcet="0" wcet="4" period="10000" deadline="10000"/>
        <task id="69" prio="69" bcet="4" wcet="92" period="10000" deadline="10000"/>
        <task id="74" prio="74" bcet="4" wcet="84" period="10000" deadline="10000"/>
        <task id="78" prio="78" bcet="3" wcet="70" period="10000" deadline="10000"/>
        <task id="86" prio="86" bcet="4" wcet="86" period="10000" deadline="10000"/>
        <task id="100" prio="100" bcet="0" wcet="12" period="10000" deadline="10000"/>
        <window start="0" stop="10000"/>
    </partition>
    <partition id="1" proc="9" maj_fr="10000">
        <task id="90" prio="90" bcet="2" wcet="56" period="10000" deadline="10000"/>
        <task id="18" prio="18" bcet="2" wcet="44" period="10000" deadline="10000"/>
        <task id="30" prio="30" bcet="3" wcet="64" period="10000" deadline="10000"/>
        <task id="33" prio="33" bcet="4" wcet="94" period="10000" deadline="10000"/>
        <task id="41" prio="41" bcet="5" wcet="100" period="10000" deadline="10000"/>
        <task id="47" prio="47" bcet="3" wcet="76" period="10000" deadline="10000"/>
        <task id="95" prio="95" bcet="1" wcet="34" period="10000" deadline="10000"/>
        <window start="0" stop="10000"/>
    </partition>
    <partition id="2" proc="5" maj_fr="10000">
        <task id="60" prio="60" bcet="3" wcet="62" period="10000" deadline="10000"/>
        <task id="55" prio="55" bcet="2" wcet="42" period="10000" deadline="10000"/>
        <task id="96" prio="96" bcet="4" wcet="80" period="10000" deadline="10000"/>
        <window start="0" stop="1467"/>
        <window start="4373" stop="5828"/>
        <window start="9338" stop="10000"/>
    </partition>
    <partition id="3" proc="5" maj_fr="10000">
        <task id="16" prio="16" bcet="0" wcet="18" period="10000" deadline="10000"/>
        <task id="19" prio="19" bcet="2" wcet="50" period="10000" deadline="10000"/>
        <window start="1467" stop="2500"/>
        <window start="5828" stop="7026"/>
    </partition>
    <partition id="4" proc="5" maj_fr="10000">
        <task id="31" prio="31" bcet="2" wcet="44" period="10000" deadline="10000"/>
        <task id="39" prio="39" bcet="3" wcet="66" period="10000" deadline="10000"/>
        <window start="2500" stop="3371"/>
        <window start="7026" stop="8139"/>
    </partition>
    <partition id="5" proc="5" maj_fr="10000">
        <task id="50" prio="50" bcet="3" wcet="76" period="10000" deadline="10000"/>
        <task id="65" prio="65" bcet="1" wcet="26" period="10000" deadline="10000"/>
        <window start="3371" stop="4373"/>
        <window start="8139" stop="9338"/>
    </partition>
    <partition id="6" proc="1" maj_fr="10000">
        <task id="13" prio="13" bcet="0" wcet="2" period="10000" deadline="10000"/>
        <task id="15" prio="15" bcet="3" wcet="70" period="10000" deadline="10000"/>
        <task id="17" prio="17" bcet="2" wcet="50" period="10000" deadline="10000"/>
        <task id="22" prio="22" bcet="4" wcet="88" period="10000" deadline="10000"/>
        <task id="36" prio="36" bcet="1" wcet="36" period="10000" deadline="10000"/>
        <task id="40" prio="40" bcet="4" wcet="92" period="10000" deadline="10000"/>
        <task id="62" prio="62" bcet="1" wcet="36" period="10000" deadline="10000"/>
        <task id="71" prio="71" bcet="2" wcet="58" period="10000" deadline="10000"/>
        <task id="93" prio="93" bcet="1" wcet="32" period="10000" deadline="10000"/>
        <task id="99" prio="99" bcet="4" wcet="90" period="10000" deadline="10000"/>
        <window start="0" stop="10000"/>
    </partition>
    <partition id="7" proc="7" maj_fr="10000">
        <task id="12" prio="12" bcet="4" wcet="80" period="10000" deadline="10000"/>
        <task id="79" prio="79" bcet="3" wcet="66" period="10000" deadline="10000"/>
        <window start="0" stop="819"/>
        <window start="2632" stop="3649"/>
        <window start="6257" stop="6889"/>
        <window start="8783" stop="10000"/>
    </partition>
    <partition id="8" proc="7" maj_fr="10000">
        <task id="97" prio="97" bcet="0" wcet="10" period="10000" deadline="10000"/>
        <task id="23" prio="23" bcet="2" wcet="50" period="10000" deadline="10000"/>
        <window start="819" stop="1459"/>
        <window start="3649" stop="5071"/>
        <window start="6889" stop="7617"/>
    </partition>
    <partition id="9" proc="7" maj_fr="10000">
        <task id="52" prio="52" bcet="4" wcet="88" period="10000" deadline="10000"/>
        <window start="1459" stop="2632"/>
        <window start="5071" stop="6257"/>
        <window start="7617" stop="8783"/>
    </partition>
    <partition id="10" proc="6" maj_fr="10000">
        <task id="91" prio="91" bcet="3" wcet="70" period="10000" deadline="10000"/>
        <task id="14" prio="14" bcet="2" wcet="54" period="10000" deadline="10000"/>
        <task id="84" prio="84" bcet="1" wcet="36" period="10000" deadline="10000"/>
        <window start="0" stop="893"/>
        <window start="1542" stop="2842"/>
        <window start="3522" stop="4257"/>
        <window start="5202" stop="6258"/>
        <window start="6850" stop="7911"/>
        <window start="8795" stop="9698"/>
    </partition>
    <partition id="11" proc="6" maj_fr="10000">
        <task id="38" prio="38" bcet="0" wcet="16" period="10000" deadline="10000"/>
        <task id="10" prio="10" bcet="3" wcet="78" period="10000" deadline="10000"/>
        <task id="26" prio="26" bcet="0" wcet="2" period="10000" deadline="10000"/>
        <window start="893" stop="1542"/>
        <window start="2842" stop="3522"/>
        <window start="4257" stop="5202"/>
        <window start="6258" stop="6850"/>
        <window start="7911" stop="8795"/>
        <window start="9698" stop="10000"/>
    </partition>
    <partition id="12" proc="8" maj_fr="10000">
        <task id="29" prio="29" bcet="4" wcet="84" period="10000" deadline="10000"/>
        <window start="0" stop="1270"/>
        <window start="3994" stop="5166"/>
        <window start="7812" stop="8323"/>
    </partition>
    <partition id="13" proc="8" maj_fr="10000">
        <task id="7" prio="7" bcet="3" wcet="78" period="10000" deadline="10000"/>
        <task id="45" prio="45" bcet="3" wcet="68" period="10000" deadline="10000"/>
        <window start="1270" stop="2659"/>
        <window start="5166" stop="5805"/>
        <window start="8323" stop="9350"/>
    </partition>
    <partition id="14" proc="8" maj_fr="10000">
        <task id="8" prio="8" bcet="0" wcet="14" period="10000" deadline="10000"/>
        <window start="2659" stop="3295"/>
        <window start="5805" stop="6617"/>
        <window start="9350" stop="10000"/>
    </partition>
    <partition id="15" proc="8" maj_fr="10000">
        <task id="56" prio="56" bcet="3" wcet="70" period="10000" deadline="10000"/>
        <window start="3295" stop="3994"/>
        <window start="6617" stop="7812"/>
    </partition>
    <partition id="16" proc="3" maj_fr="10000">
        <task id="6" prio="6" bcet="3" wcet="64" period="10000" deadline="10000"/>
        <window start="0" stop="1285"/>
        <window start="3672" stop="4256"/>
        <window start="8178" stop="8701"/>
    </partition>
    <partition id="17" proc="3" maj_fr="10000">
        <task id="43" prio="43" bcet="2" wcet="56" period="10000" deadline="10000"/>
        <task id="89" prio="89" bcet="3" wcet="62" period="10000" deadline="10000"/>
        <window start="1285" stop="1905"/>
        <window start="4256" stop="5338"/>
        <window start="8701" stop="9662"/>
    </partition>
    <partition id="18" proc="3" maj_fr="10000">
        <task id="11" prio="11" bcet="0" wcet="16" period="10000" deadline="10000"/>
        <task id="80" prio="80" bcet="4" wcet="92" period="10000" deadline="10000"/>
        <window start="1905" stop="2719"/>
        <window start="5338" stop="6695"/>
        <window start="9662" stop="10000"/>
    </partition>
    <partition id="19" proc="3" maj_fr="10000">
        <task id="98" prio="98" bcet="2" wcet="42" period="10000" deadline="10000"/>
        <task id="82" prio="82" bcet="2" wcet="46" period="10000" deadline="10000"/>
        <window start="2719" stop="3672"/>
        <window start="6695" stop="8178"/>
    </partition>
    <partition id="20" proc="4" maj_fr="10000">
        <task id="68" prio="68" bcet="3" wcet="78" period="10000" deadline="10000"/>
        <task id="32" prio="32" bcet="2" wcet="46" period="10000" deadline="10000"/>
        <task id="64" prio="64" bcet="0" wcet="18" period="10000" deadline="10000"/>
        <task id="72" prio="72" bcet="2" wcet="58" period="10000" deadline="10000"/>
        <task id="81" prio="81" bcet="3" wcet="76" period="10000" deadline="10000"/>
        <task id="85" prio="85" bcet="0" wcet="6" period="10000" deadline="10000"/>
        <window start="0" stop="994"/>
        <window start="3386" stop="4723"/>
        <window start="6407" stop="7803"/>
        <window start="9620" stop="10000"/>
    </partition>
    <partition id="21" proc="4" maj_fr="10000">
        <task id="73" prio="73" bcet="0" wcet="16" period="10000" deadline="10000"/>
        <task id="27" prio="27" bcet="0" wcet="4" period="10000" deadline="10000"/>
        <task id="63" prio="63" bcet="2" wcet="58" period="10000" deadline="10000"/>
        <window start="994" stop="1906"/>
        <window start="4723" stop="5650"/>
        <window start="7803" stop="8489"/>
    </partition>
    <partition id="22" proc="4" maj_fr="10000">
        <task id="4" prio="4" bcet="4" wcet="82" period="10000" deadline="10000"/>
        <task id="20" prio="20" bcet="4" wcet="80" period="10000" deadline="10000"/>
        <task id="42" prio="42" bcet="1" wcet="38" period="10000" deadline="10000"/>
        <task id="48" prio="48" bcet="4" wcet="98" period="10000" deadline="10000"/>
        <task id="53" prio="53" bcet="4" wcet="88" period="10000" deadline="10000"/>
        <window start="1906" stop="3386"/>
        <window start="5650" stop="6407"/>
        <window start="8489" stop="9620"/>
    </partition>
    <partition id="23" proc="2" maj_fr="10000">
        <task id="44" prio="44" bcet="0" wcet="6" period="10000" deadline="10000"/>
        <window start="0" stop="1455"/>
        <window start="3274" stop="4078"/>
        <window start="7636" stop="8946"/>
    </partition>
    <partition id="24" proc="2" maj_fr="10000">
        <task id="3" prio="3" bcet="1" wcet="22" period="10000" deadline="10000"/>
        <window start="1455" stop="2036"/>
        <window start="4078" stop="5516"/>
        <window start="8946" stop="10000"/>
    </partition>
    <partition id="25" proc="2" maj_fr="10000">
        <task id="34" prio="34" bcet="1" wcet="36" period="10000" deadline="10000"/>
        <window start="2036" stop="2772"/>
        <window start="5516" stop="6927"/>
    </partition>
    <partition id="26" proc="2" maj_fr="10000">
        <task id="66" prio="66" bcet="2" wcet="48" period="10000" deadline="10000"/>
        <window start="2772" stop="3274"/>
        <window start="6927" stop="7636"/>
    </partition>
    <partition id="27" proc="11" maj_fr="10000">
        <task id="49" prio="49" bcet="5" wcet="100" period="10000" deadline="10000"/>
        <task id="2" prio="2" bcet="1" wcet="28" period="10000" deadline="10000"/>
        <window start="0" stop="1104"/>
        <window start="2420" stop="3441"/>
        <window start="4864" stop="5874"/>
        <window start="6903" stop="7546"/>
        <window start="8808" stop="9823"/>
    </partition>
    <partition id="28" proc="11" maj_fr="10000">
        <task id="94" prio="94" bcet="0" wcet="6" period="10000" deadline="10000"/>
        <task id="21" prio="21" bcet="4" wcet="96" period="10000" deadline="10000"/>
        <task id="87" prio="87" bcet="4" wcet="96" period="10000" deadline="10000"/>
        <task id="88" prio="88" bcet="3" wcet="66" period="10000" deadline="10000"/>
        <task id="92" prio="92" bcet="2" wcet="52" period="10000" deadline="10000"/>
        <window start="1104" stop="2420"/>
        <window start="3441" stop="4864"/>
        <window start="5874" stop="6903"/>
        <window start="7546" stop="8808"/>
        <window start="9823" stop="10000"/>
    </partition>
    <partition id="29" proc="0" maj_fr="10000">
        <task id="70" prio="70" bcet="1" wcet="30" period="10000" deadline="10000"/>
        <task id="5" prio="5" bcet="3" wcet="76" period="10000" deadline="10000"/>
        <task id="9" prio="9" bcet="0" wcet="6" period="10000" deadline="10000"/>
        <task id="51" prio="51" bcet="1" wcet="20" period="10000" deadline="10000"/>
        <task id="59" prio="59" bcet="0" wcet="10" period="10000" deadline="10000"/>
        <task id="67" prio="67" bcet="0" wcet="2" period="10000" deadline="10000"/>
        <task id="76" prio="76" bcet="0" wcet="16" period="10000" deadline="10000"/>
        <task id="77" prio="77" bcet="2" wcet="52" period="10000" deadline="10000"/>
        <task id="83" prio="83" bcet="4" wcet="94" period="10000" deadline="10000"/>
        <window start="0" stop="10000"/>
    </partition>
    <partition id="30" proc="10" maj_fr="10000">
        <task id="61" prio="61" bcet="1" wcet="30" period="10000" deadline="10000"/>
        <task id="0" prio="0" bcet="0" wcet="16" period="10000" deadline="10000"/>
        <task id="54" prio="54" bcet="2" wcet="48" period="10000" deadline="10000"/>
        <window start="0" stop="1093"/>
        <window start="1963" stop="3143"/>
        <window start="4636" stop="5967"/>
        <window start="7357" stop="8255"/>
        <window start="9280" stop="10000"/>
    </partition>
    <partition id="31" proc="10" maj_fr="10000">
        <task id="57" prio="57" bcet="4" wcet="94" period="10000" deadline="10000"/>
        <task id="1" prio="1" bcet="0" wcet="14" period="10000" deadline="10000"/>
        <task id="58" prio="58" bcet="3" wcet="64" period="10000" deadline="10000"/>
        <task id="75" prio="75" bcet="1" wcet="38" period="10000" deadline="10000"/>
        <window start="1093" stop="1963"/>
        <window start="3143" stop="4636"/>
        <window start="5967" stop="7357"/>
        <window start="8255" stop="9280"/>
    </partition>
    <tlink src="25" dist="1" bctt="0" wctt="6"/>
    <tlink src="25" dist="3" bctt="3" wctt="42"/>
    <tlink src="25" dist="5" bctt="3" wctt="4"/>
    <tlink src="25" dist="7" bctt="51" wctt="58"/>
    <tlink src="25" dist="9" bctt="1" wctt="68"/>
    <tlink src="25" dist="11" bctt="35" wctt="53"/>
    <tlink src="25" dist="13" bctt="64" wctt="81"/>
    <tlink src="25" dist="14" bctt="5" wctt="74"/>
    <tlink src="25" dist="15" bctt="50" wctt="78"/>
    <tlink src="25" dist="16" bctt="37" wctt="44"/>
    <tlink src="25" dist="18" bctt="63" wctt="91"/>
    <tlink src="25" dist="20" bctt="17" wctt="27"/>
    <tlink src="25" dist="21" bctt="15" wctt="15"/>
    <tlink src="25" dist="23" bctt="39" wctt="41"/>
    <tlink src="25" dist="31" bctt="0" wctt="6"/>
    <tlink src="25" dist="32" bctt="18" wctt="35"/>
    <tlink src="25" dist="33" bctt="0" wctt="1"/>
    <tlink src="25" dist="45" bctt="6" wctt="17"/>
    <tlink src="25" dist="48" bctt="86" wctt="91"/>
    <tlink src="25" dist="49" bctt="18" wctt="19"/>
    <tlink src="25" dist="50" bctt="0" wctt="6"/>
    <tlink src="25" dist="51" bctt="18" wctt="83"/>
    <tlink src="25" dist="60" bctt="30" wctt="70"/>
    <tlink src="25" dist="68" bctt="16" wctt="52"/>
    <tlink src="25" dist="71" bctt="54" wctt="66"/>
    <tlink src="25" dist="75" bctt="15" wctt="57"/>
    <tlink src="25" dist="76" bctt="39" wctt="65"/>
    <tlink src="25" dist="81" bctt="85" wctt="91"/>
    <tlink src="25" dist="87" bctt="27" wctt="34"/>
    <tlink src="25" dist="96" bctt="4" wctt="7"/>
    <tlink src="25" dist="100" bctt="16" wctt="62"/>
    <tlink src="26" dist="1" bctt="49" wctt="86"/>
    <tlink src="26" dist="4" bctt="46" wctt="67"/>
    <tlink src="26" dist="5" bctt="36" wctt="89"/>
    <tlink src="26" dist="7" bctt="9" wctt="48"/>
    <tlink src="26" dist="8" bctt="41" wctt="93"/>
    <tlink src="26" dist="9" bctt="3" wctt="11"/>
    <tlink src="26" dist="11" bctt="11" wctt="94"/>
    <tlink src="26" dist="12" bctt="69" wctt="90"/>
    <tlink src="26" dist="13" bctt="32" wctt="32"/>
    <tlink src="26" dist="14" bctt="6" wctt="75"/>
    <tlink src="26" dist="16" bctt="11" wctt="20"/>
    <tlink src="26" dist="17" bctt="32" wctt="34"/>
    <tlink src="26" dist="19" bctt="51" wctt="69"/>
    <tlink src="26" dist="20" bctt="7" wctt="33"/>
    <tlink src="26" dist="22" bctt="8" wctt="24"/>
    <tlink src="26" dist="27" bctt="27" wctt="29"/>
    <tlink src="26" dist="29" bctt="7" wctt="7"/>
    <tlink src="26" dist="34" bctt="8" wctt="17"/>
    <tlink src="26" dist="37" bctt="21" wctt="25"/>
    <tlink src="26" dist="42" bctt="12" wctt="13"/>
    <tlink src="26" dist="43" bctt="3" wctt="43"/>
    <tlink src="26" dist="47" bctt="39" wctt="49"/>
    <tlink src="26" dist="53" bctt="12" wctt="18"/>
    <tlink src="26" dist="62" bctt="4" wctt="6"/>
    <tlink src="26" dist="70" bctt="1" wctt="1"/>
    <tlink src="26" dist="80" bctt="42" wctt="95"/>
    <tlink src="26" dist="89" bctt="18" wctt="50"/>
    <tlink src="27" dist="2" bctt="56" wctt="100"/>
    <tlink src="27" dist="3" bctt="32" wctt="54"/>
    <tlink src="27" dist="9" bctt="12" wctt="40"/>
    <tlink src="27" dist="11" bctt="11" wctt="31"/>
    <tlink src="27" dist="13" bctt="1" wctt="1"/>
    <tlink src="27" dist="14" bctt="30" wctt="66"/>
    <tlink src="27" dist="15" bctt="10" wctt="60"/>
    <tlink src="27" dist="17" bctt="3" wctt="12"/>
    <tlink src="27" dist="21" bctt="11" wctt="75"/>
    <tlink src="27" dist="24" bctt="38" wctt="53"/>
    <tlink src="27" dist="35" bctt="14" wctt="27"/>
    <tlink src="27" dist="41" bctt="57" wctt="63"/>
    <tlink src="27" dist="44" bctt="19" wctt="39"/>
    <tlink src="27" dist="55" bctt="25" wctt="96"/>
    <tlink src="27" dist="57" bctt="0" wctt="13"/>
    <tlink src="27" dist="61" bctt="1" wctt="1"/>
    <tlink src="27" dist="65" bctt="57" wctt="59"/>
    <tlink src="27" dist="69" bctt="0" wctt="40"/>
    <tlink src="27" dist="73" bctt="45" wctt="63"/>
    <tlink src="27" dist="86" bctt="12" wctt="14"/>
    <tlink src="27" dist="92" bctt="18" wctt="78"/>
    <tlink src="27" dist="93" bctt="1" wctt="28"/>
    <tlink src="27" dist="95" bctt="1" wctt="2"/>
    <tlink src="27" dist="99" bctt="7" wctt="13"/>
    <tlink src="28" dist="0" bctt="1" wctt="28"/>
    <tlink src="28" dist="1" bctt="9" wctt="37"/>
    <tlink src="28" dist="2" bctt="21" wctt="26"/>
    <tlink src="28" dist="3" bctt="32" wctt="79"/>
    <tlink src="28" dist="5" bctt="61" wctt="79"/>
    <tlink src="28" dist="6" bctt="18" wctt="21"/>
    <tlink src="28" dist="9" bctt="51" wctt="91"/>
    <tlink src="28" dist="10" bctt="6" wctt="7"/>
    <tlink src="28" dist="11" bctt="20" wctt="81"/>
    <tlink src="28" dist="12" bctt="15" wctt="37"/>
    <tlink src="28" dist="15" bctt="2" wctt="14"/>
    <tlink src="28" dist="17" bctt="51" wctt="76"/>
    <tlink src="28" dist="21" bctt="13" wctt="99"/>
    <tlink src="28" dist="22" bctt="17" wctt="62"/>
    <tlink src="28" dist="36" bctt="27" wctt="50"/>
    <tlink src="28" dist="38" bctt="39" wctt="39"/>
    <tlink src="28" dist="40" bctt="9" wctt="20"/>
    <tlink src="28" dist="59" bctt="0" wctt="39"/>
    <tlink src="28" dist="72" bctt="80" wctt="96"/>
    <tlink src="28" dist="83" bctt="13" wctt="32"/>
    <tlink src="28" dist="85" bctt="11" wctt="34"/>
    <tlink src="28" dist="98" bctt="28" wctt="42"/>
    <tlink src="29" dist="0" bctt="32" wctt="38"/>
    <tlink src="29" dist="1" bctt="6" wctt="46"/>
    <tlink src="29" dist="2" bctt="31" wctt="51"/>
    <tlink src="29" dist="66" bctt="49" wctt="78"/>
    <tlink src="29" dist="67" bctt="7" wctt="38"/>
    <tlink src="29" dist="5" bctt="66" wctt="74"/>
    <tlink src="29" dist="7" bctt="4" wctt="34"/>
    <tlink src="29" dist="74" bctt="61" wctt="63"/>
    <tlink src="29" dist="12" bctt="3" wctt="6"/>
    <tlink src="29" dist="13" bctt="12" wctt="14"/>
    <tlink src="29" dist="14" bctt="29" wctt="35"/>
    <tlink src="29" dist="18" bctt="10" wctt="13"/>
    <tlink src="29" dist="19" bctt="17" wctt="33"/>
    <tlink src="29" dist="82" bctt="79" wctt="93"/>
    <tlink src="29" dist="84" bctt="18" wctt="56"/>
    <tlink src="29" dist="22" bctt="27" wctt="75"/>
    <tlink src="30" dist="1" bctt="30" wctt="68"/>
    <tlink src="30" dist="3" bctt="24" wctt="43"/>
    <tlink src="30" dist="4" bctt="56" wctt="83"/>
    <tlink src="30" dist="5" bctt="14" wctt="66"/>
    <tlink src="30" dist="6" bctt="53" wctt="74"/>
    <tlink src="30" dist="7" bctt="24" wctt="35"/>
    <tlink src="30" dist="8" bctt="30" wctt="76"/>
    <tlink src="30" dist="9" bctt="10" wctt="46"/>
    <tlink src="30" dist="10" bctt="52" wctt="52"/>
    <tlink src="30" dist="11" bctt="8" wctt="20"/>
    <tlink src="30" dist="12" bctt="46" wctt="50"/>
    <tlink src="30" dist="13" bctt="50" wctt="81"/>
    <tlink src="30" dist="14" bctt="51" wctt="90"/>
    <tlink src="30" dist="16" bctt="39" wctt="46"/>
    <tlink src="30" dist="18" bctt="0" wctt="24"/>
    <tlink src="30" dist="20" bctt="48" wctt="59"/>
    <tlink src="30" dist="23" bctt="43" wctt="59"/>
    <tlink src="30" dist="54" bctt="21" wctt="71"/>
    <tlink src="30" dist="58" bctt="6" wctt="45"/>
    <tlink src="30" dist="64" bctt="10" wctt="16"/>
    <tlink src="30" dist="79" bctt="10" wctt="36"/>
    <tlink src="30" dist="88" bctt="21" wctt="98"/>
    <tlink src="30" dist="91" bctt="13" wctt="97"/>
    <tlink src="30" dist="97" bctt="52" wctt="65"/>
    <tlink src="31" dist="2" bctt="79" wctt="85"/>
    <tlink src="31" dist="3" bctt="26" wctt="40"/>
    <tlink src="31" dist="4" bctt="17" wctt="56"/>
    <tlink src="31" dist="5" bctt="25" wctt="33"/>
    <tlink src="31" dist="6" bctt="14" wctt="42"/>
    <tlink src="31" dist="7" bctt="48" wctt="58"/>
    <tlink src="31" dist="8" bctt="10" wctt="76"/>
    <tlink src="31" dist="9" bctt="24" wctt="31"/>
    <tlink src="31" dist="10" bctt="28" wctt="68"/>
    <tlink src="31" dist="13" bctt="9" wctt="22"/>
    <tlink src="31" dist="46" bctt="28" wctt="31"/>
    <tlink src="31" dist="77" bctt="14" wctt="68"/>
    <tlink src="31" dist="17" bctt="9" wctt="10"/>
    <tlink src="31" dist="19" bctt="22" wctt="41"/>
    <tlink src="31" dist="22" bctt="18" wctt="24"/>
    <tlink src="31" dist="94" bctt="62" wctt="97"/>
    <tlink src="32" dist="0" bctt="44" wctt="95"/>
    <tlink src="32" dist="1" bctt="39" wctt="69"/>
    <tlink src="32" dist="2" bctt="59" wctt="93"/>
    <tlink src="32" dist="5" bctt="8" wctt="54"/>
    <tlink src="32" dist="7" bctt="7" wctt="25"/>
    <tlink src="32" dist="8" bctt="9" wctt="38"/>
    <tlink src="32" dist="9" bctt="9" wctt="38"/>
    <tlink src="32" dist="10" bctt="51" wctt="71"/>
    <tlink src="32" dist="11" bctt="1" wctt="24"/>
    <tlink src="32" dist="12" bctt="9" wctt="80"/>
    <tlink src="32" dist="14" bctt="39" wctt="47"/>
    <tlink src="32" dist="15" bctt="7" wctt="98"/>
    <tlink src="32" dist="18" bctt="47" wctt="87"/>
    <tlink src="32" dist="52" bctt="12" wctt="19"/>
    <tlink src="32" dist="22" bctt="21" wctt="59"/>
    <tlink src="32" dist="24" bctt="0" wctt="1"/>
    <tlink src="32" dist="56" bctt="2" wctt="28"/>
    <tlink src="33" dist="0" bctt="35" wctt="43"/>
    <tlink src="33" dist="1" bctt="3" wctt="25"/>
    <tlink src="33" dist="4" bctt="15" wctt="57"/>
    <tlink src="33" dist="5" bctt="17" wctt="93"/>
    <tlink src="33" dist="6" bctt="23" wctt="49"/>
    <tlink src="33" dist="7" bctt="54" wctt="54"/>
    <tlink src="33" dist="9" bctt="21" wctt="22"/>
    <tlink src="33" dist="10" bctt="14" wctt="43"/>
    <tlink src="33" dist="11" bctt="41" wctt="56"/>
    <tlink src="33" dist="13" bctt="62" wctt="89"/>
    <tlink src="33" dist="15" bctt="2" wctt="11"/>
    <tlink src="33" dist="16" bctt="25" wctt="50"/>
    <tlink src="33" dist="17" bctt="53" wctt="80"/>
    <tlink src="33" dist="20" bctt="9" wctt="39"/>
    <tlink src="33" dist="21" bctt="72" wctt="99"/>
    <tlink src="33" dist="23" bctt="10" wctt="23"/>
    <tlink src="33" dist="24" bctt="0" wctt="11"/>
    <tlink src="34" dist="1" bctt="5" wctt="93"/>
    <tlink src="34" dist="2" bctt="31" wctt="67"/>
    <tlink src="34" dist="3" bctt="18" wctt="18"/>
    <tlink src="34" dist="4" bctt="28" wctt="36"/>
    <tlink src="34" dist="5" bctt="20" wctt="72"/>
    <tlink src="34" dist="8" bctt="14" wctt="46"/>
    <tlink src="34" dist="11" bctt="5" wctt="15"/>
    <tlink src="34" dist="14" bctt="21" wctt="63"/>
    <tlink src="34" dist="78" bctt="38" wctt="85"/>
    <tlink src="34" dist="16" bctt="24" wctt="33"/>
    <tlink src="34" dist="17" bctt="45" wctt="97"/>
    <tlink src="34" dist="18" bctt="55" wctt="89"/>
    <tlink src="34" dist="19" bctt="19" wctt="21"/>
    <tlink src="34" dist="22" bctt="24" wctt="41"/>
    <tlink src="34" dist="24" bctt="36" wctt="45"/>
    <tlink src="35" dist="0" bctt="31" wctt="32"/>
    <tlink src="35" dist="1" bctt="32" wctt="35"/>
    <tlink src="35" dist="3" bctt="11" wctt="19"/>
    <tlink src="35" dist="4" bctt="8" wctt="96"/>
    <tlink src="35" dist="5" bctt="2" wctt="2"/>
    <tlink src="35" dist="6" bctt="48" wctt="66"/>
    <tlink src="35" dist="7" bctt="20" wctt="97"/>
    <tlink src="35" dist="8" bctt="34" wctt="91"/>
    <tlink src="35" dist="39" bctt="7" wctt="14"/>
    <tlink src="35" dist="10" bctt="55" wctt="62"/>
    <tlink src="35" dist="11" bctt="74" wctt="85"/>
    <tlink src="35" dist="12" bctt="36" wctt="58"/>
    <tlink src="35" dist="15" bctt="1" wctt="65"/>
    <tlink src="35" dist="17" bctt="9" wctt="16"/>
    <tlink src="35" dist="18" bctt="17" wctt="27"/>
    <tlink src="35" dist="23" bctt="15" wctt="65"/>
    <tlink src="36" dist="0" bctt="9" wctt="25"/>
    <tlink src="36" dist="1" bctt="28" wctt="45"/>
    <tlink src="36" dist="11" bctt="2" wctt="2"/>
    <tlink src="36" dist="12" bctt="1" wctt="1"/>
    <tlink src="36" dist="15" bctt="58" wctt="62"/>
    <tlink src="36" dist="16" bctt="16" wctt="76"/>
    <tlink src="36" dist="17" bctt="18" wctt="33"/>
    <tlink src="36" dist="19" bctt="37" wctt="54"/>
    <tlink src="36" dist="20" bctt="7" wctt="47"/>
    <tlink src="36" dist="21" bctt="64" wctt="69"/>
    <tlink src="36" dist="22" bctt="24" wctt="56"/>
    <tlink src="36" dist="23" bctt="23" wctt="99"/>
    <tlink src="37" dist="0" bctt="67" wctt="88"/>
    <tlink src="37" dist="3" bctt="34" wctt="86"/>
    <tlink src="37" dist="4" bctt="13" wctt="19"/>
    <tlink src="37" dist="5" bctt="2" wctt="7"/>
    <tlink src="37" dist="7" bctt="19" wctt="27"/>
    <tlink src="37" dist="8" bctt="1" wctt="2"/>
    <tlink src="37" dist="9" bctt="10" wctt="62"/>
    <tlink src="37" dist="11" bctt="85" wctt="86"/>
    <tlink src="37" dist="13" bctt="4" wctt="58"/>
    <tlink src="37" dist="15" bctt="0" wctt="15"/>
    <tlink src="37" dist="16" bctt="27" wctt="98"/>
    <tlink src="37" dist="17" bctt="36" wctt="37"/>
    <tlink src="37" dist="18" bctt="48" wctt="54"/>
    <tlink src="37" dist="19" bctt="11" wctt="75"/>
    <tlink src="37" dist="20" bctt="5" wctt="77"/>
    <tlink src="37" dist="21" bctt="41" wctt="46"/>
    <tlink src="37" dist="22" bctt="83" wctt="97"/>
    <tlink src="37" dist="23" bctt="6" wctt="8"/>
    <tlink src="37" dist="24" bctt="13" wctt="39"/>
    <tlink src="38" dist="5" bctt="0" wctt="2"/>
    <tlink src="38" dist="10" bctt="14" wctt="55"/>
    <tlink src="38" dist="11" bctt="0" wctt="1"/>
    <tlink src="38" dist="13" bctt="44" wctt="64"/>
    <tlink src="38" dist="14" bctt="20" wctt="37"/>
    <tlink src="38" dist="15" bctt="32" wctt="43"/>
    <tlink src="38" dist="16" bctt="6" wctt="37"/>
    <tlink src="38" dist="19" bctt="21" wctt="41"/>
    <tlink src="38" dist="22" bctt="10" wctt="65"/>
    <tlink src="38" dist="23" bctt="6" wctt="33"/>
    <tlink src="38" dist="90" bctt="3" wctt="55"/>
    <tlink src="39" dist="2" bctt="2" wctt="2"/>
    <tlink src="39" dist="4" bctt="28" wctt="34"/>
    <tlink src="39" dist="6" bctt="3" wctt="3"/>
    <tlink src="39" dist="7" bctt="64" wctt="80"/>
    <tlink src="39" dist="9" bctt="18" wctt="20"/>
    <tlink src="39" dist="11" bctt="11" wctt="22"/>
    <tlink src="39" dist="16" bctt="53" wctt="59"/>
    <tlink src="39" dist="17" bctt="25" wctt="60"/>
    <tlink src="39" dist="19" bctt="24" wctt="82"/>
    <tlink src="39" dist="21" bctt="75" wctt="84"/>
    <tlink src="39" dist="23" bctt="74" wctt="92"/>
    <tlink src="39" dist="24" bctt="11" wctt="33"/>
    <tlink src="40" dist="0" bctt="13" wctt="23"/>
    <tlink src="40" dist="3" bctt="72" wctt="90"/>
    <tlink src="40" dist="4" bctt="3" wctt="6"/>
    <tlink src="40" dist="5" bctt="2" wctt="4"/>
    <tlink src="40" dist="7" bctt="28" wctt="83"/>
    <tlink src="40" dist="10" bctt="65" wctt="65"/>
    <tlink src="40" dist="12" bctt="22" wctt="59"/>
    <tlink src="40" dist="14" bctt="2" wctt="10"/>
    <tlink src="40" dist="16" bctt="17" wctt="84"/>
    <tlink src="40" dist="17" bctt="1" wctt="10"/>
    <tlink src="40" dist="18" bctt="2" wctt="6"/>
    <tlink src="40" dist="19" bctt="2" wctt="8"/>
    <tlink src="40" dist="21" bctt="26" wctt="28"/>
    <tlink src="40" dist="24" bctt="28" wctt="41"/>
    <tlink src="41" dist="0" bctt="2" wctt="70"/>
    <tlink src="41" dist="1" bctt="37" wctt="40"/>
    <tlink src="41" dist="4" bctt="26" wctt="59"/>
    <tlink src="41" dist="5" bctt="1" wctt="6"/>
    <tlink src="41" dist="7" bctt="1" wctt="18"/>
    <tlink src="41" dist="9" bctt="8" wctt="10"/>
    <tlink src="41" dist="10" bctt="57" wctt="63"/>
    <tlink src="41" dist="14" bctt="50" wctt="54"/>
    <tlink src="41" dist="15" bctt="1" wctt="1"/>
    <tlink src="41" dist="18" bctt="3" wctt="9"/>
    <tlink src="41" dist="20" bctt="16" wctt="32"/>
    <tlink src="41" dist="21" bctt="27" wctt="73"/>
    <tlink src="41" dist="22" bctt="61" wctt="65"/>
    <tlink src="41" dist="23" bctt="17" wctt="50"/>
    <tlink src="41" dist="24" bctt="36" wctt="69"/>
    <tlink src="42" dist="0" bctt="47" wctt="53"/>
    <tlink src="42" dist="4" bctt="50" wctt="90"/>
    <tlink src="42" dist="5" bctt="0" wctt="16"/>
    <tlink src="42" dist="7" bctt="48" wctt="98"/>
    <tlink src="42" dist="8" bctt="12" wctt="49"/>
    <tlink src="42" dist="9" bctt="1" wctt="68"/>
    <tlink src="42" dist="10" bctt="4" wctt="17"/>
    <tlink src="42" dist="13" bctt="67" wctt="71"/>
    <tlink src="42" dist="15" bctt="61" wctt="95"/>
    <tlink src="42" dist="17" bctt="8" wctt="80"/>
    <tlink src="42" dist="23" bctt="11" wctt="96"/>
    <tlink src="42" dist="24" bctt="23" wctt="31"/>
    <tlink src="43" dist="0" bctt="18" wctt="70"/>
    <tlink src="43" dist="1" bctt="27" wctt="33"/>
    <tlink src="43" dist="3" bctt="28" wctt="72"/>
    <tlink src="43" dist="4" bctt="15" wctt="47"/>
    <tlink src="43" dist="5" bctt="28" wctt="53"/>
    <tlink src="43" dist="6" bctt="77" wctt="98"/>
    <tlink src="43" dist="10" bctt="33" wctt="76"/>
    <tlink src="43" dist="15" bctt="30" wctt="52"/>
    <tlink src="43" dist="16" bctt="27" wctt="34"/>
    <tlink src="43" dist="17" bctt="67" wctt="80"/>
    <tlink src="43" dist="18" bctt="7" wctt="50"/>
    <tlink src="43" dist="19" bctt="79" wctt="90"/>
    <tlink src="43" dist="20" bctt="1" wctt="22"/>
    <tlink src="43" dist="24" bctt="71" wctt="89"/>
    <tlink src="44" dist="0" bctt="60" wctt="60"/>
    <tlink src="44" dist="3" bctt="20" wctt="86"/>
    <tlink src="44" dist="4" bctt="24" wctt="24"/>
    <tlink src="44" dist="5" bctt="16" wctt="21"/>
    <tlink src="44" dist="11" bctt="11" wctt="17"/>
    <tlink src="44" dist="13" bctt="16" wctt="26"/>
    <tlink src="44" dist="16" bctt="46" wctt="53"/>
    <tlink src="44" dist="21" bctt="80" wctt="90"/>
    <tlink src="44" dist="22" bctt="1" wctt="63"/>
    <tlink src="44" dist="23" bctt="1" wctt="26"/>
    <tlink src="44" dist="24" bctt="31" wctt="91"/>
    <tlink src="45" dist="1" bctt="14" wctt="23"/>
    <tlink src="45" dist="5" bctt="30" wctt="90"/>
    <tlink src="45" dist="6" bctt="20" wctt="68"/>
    <tlink src="45" dist="9" bctt="26" wctt="41"/>
    <tlink src="45" dist="11" bctt="69" wctt="75"/>
    <tlink src="45" dist="12" bctt="49" wctt="83"/>
    <tlink src="45" dist="13" bctt="11" wctt="46"/>
    <tlink src="45" dist="14" bctt="10" wctt="10"/>
    <tlink src="45" dist="15" bctt="41" wctt="75"/>
    <tlink src="45" dist="17" bctt="3" wctt="13"/>
    <tlink src="45" dist="19" bctt="37" wctt="89"/>
    <tlink src="45" dist="20" bctt="0" wctt="52"/>
    <tlink src="45" dist="22" bctt="10" wctt="40"/>
    <tlink src="45" dist="23" bctt="3" wctt="5"/>
    <tlink src="45" dist="24" bctt="5" wctt="5"/>
    <tlink src="46" dist="0" bctt="40" wctt="40"/>
    <tlink src="46" dist="1" bctt="1" wctt="1"/>
    <tlink src="46" dist="3" bctt="16" wctt="35"/>
    <tlink src="46" dist="5" bctt="3" wctt="3"/>
    <tlink src="46" dist="6" bctt="10" wctt="39"/>
    <tlink src="46" dist="7" bctt="15" wctt="34"/>
    <tlink src="46" dist="9" bctt="23" wctt="36"/>
    <tlink src="46" dist="10" bctt="36" wctt="58"/>
    <tlink src="46" dist="15" bctt="29" wctt="31"/>
    <tlink src="46" dist="16" bctt="0" wctt="1"/>
    <tlink src="46" dist="18" bctt="45" wctt="55"/>
    <tlink src="46" dist="22" bctt="12" wctt="18"/>
    <tlink src="46" dist="23" bctt="40" wctt="62"/>
    <tlink src="47" dist="0" bctt="10" wctt="59"/>
    <tlink src="47" dist="1" bctt="21" wctt="92"/>
    <tlink src="47" dist="3" bctt="34" wctt="74"/>
    <tlink src="47" dist="7" bctt="21" wctt="99"/>
    <tlink src="47" dist="8" bctt="1" wctt="48"/>
    <tlink src="47" dist="9" bctt="12" wctt="61"/>
    <tlink src="47" dist="10" bctt="31" wctt="76"/>
    <tlink src="47" dist="11" bctt="59" wctt="81"/>
    <tlink src="47" dist="12" bctt="18" wctt="21"/>
    <tlink src="47" dist="15" bctt="18" wctt="19"/>
    <tlink src="47" dist="16" bctt="45" wctt="90"/>
    <tlink src="47" dist="18" bctt="5" wctt="75"/>
    <tlink src="47" dist="19" bctt="51" wctt="85"/>
    <tlink src="47" dist="21" bctt="36" wctt="94"/>
    <tlink src="48" dist="1" bctt="40" wctt="46"/>
    <tlink src="48" dist="2" bctt="66" wctt="93"/>
    <tlink src="48" dist="5" bctt="45" wctt="78"/>
    <tlink src="48" dist="7" bctt="36" wctt="52"/>
    <tlink src="48" dist="9" bctt="26" wctt="27"/>
    <tlink src="48" dist="10" bctt="6" wctt="24"/>
    <tlink src="48" dist="11" bctt="39" wctt="60"/>
    <tlink src="48" dist="12" bctt="47" wctt="54"/>
    <tlink src="48" dist="13" bctt="5" wctt="13"/>
    <tlink src="48" dist="14" bctt="2" wctt="41"/>
    <tlink src="48" dist="18" bctt="34" wctt="99"/>
    <tlink src="48" dist="19" bctt="15" wctt="60"/>
    <tlink src="48" dist="20" bctt="15" wctt="31"/>
    <tlink src="48" dist="23" bctt="25" wctt="29"/>
    <tlink src="49" dist="0" bctt="36" wctt="98"/>
    <tlink src="49" dist="1" bctt="0" wctt="4"/>
    <tlink src="49" dist="2" bctt="17" wctt="25"/>
    <tlink src="49" dist="3" bctt="9" wctt="85"/>
    <tlink src="49" dist="4" bctt="42" wctt="94"/>
    <tlink src="49" dist="5" bctt="21" wctt="79"/>
    <tlink src="49" dist="6" bctt="50" wctt="63"/>
    <tlink src="49" dist="7" bctt="48" wctt="70"/>
    <tlink src="49" dist="9" bctt="12" wctt="36"/>
    <tlink src="49" dist="10" bctt="20" wctt="22"/>
    <tlink src="49" dist="11" bctt="20" wctt="44"/>
    <tlink src="49" dist="12" bctt="39" wctt="87"/>
    <tlink src="49" dist="14" bctt="8" wctt="39"/>
    <tlink src="49" dist="16" bctt="0" wctt="5"/>
    <tlink src="49" dist="17" bctt="20" wctt="35"/>
    <tlink src="49" dist="21" bctt="22" wctt="57"/>
    <tlink src="49" dist="22" bctt="40" wctt="82"/>
    <tlink src="49" dist="23" bctt="9" wctt="13"/>
    <tlink src="49" dist="24" bctt="68" wctt="72"/>
    <tlink src="50" dist="0" bctt="11" wctt="31"/>
    <tlink src="50" dist="3" bctt="35" wctt="52"/>
    <tlink src="50" dist="5" bctt="5" wctt="39"/>
    <tlink src="50" dist="7" bctt="1" wctt="56"/>
    <tlink src="50" dist="10" bctt="34" wctt="96"/>
    <tlink src="50" dist="13" bctt="36" wctt="48"/>
    <tlink src="50" dist="18" bctt="22" wctt="52"/>
    <tlink src="50" dist="19" bctt="26" wctt="49"/>
    <tlink src="50" dist="20" bctt="68" wctt="97"/>
    <tlink src="50" dist="22" bctt="6" wctt="42"/>
    <tlink src="51" dist="3" bctt="17" wctt="66"/>
    <tlink src="51" dist="7" bctt="10" wctt="46"/>
    <tlink src="51" dist="8" bctt="22" wctt="82"/>
    <tlink src="51" dist="9" bctt="28" wctt="67"/>
    <tlink src="51" dist="10" bctt="1" wctt="2"/>
    <tlink src="51" dist="11" bctt="92" wctt="93"/>
    <tlink src="51" dist="12" bctt="5" wctt="9"/>
    <tlink src="51" dist="13" bctt="4" wctt="60"/>
    <tlink src="51" dist="15" bctt="34" wctt="86"/>
    <tlink src="51" dist="16" bctt="40" wctt="52"/>
    <tlink src="51" dist="17" bctt="14" wctt="32"/>
    <tlink src="51" dist="18" bctt="98" wctt="100"/>
    <tlink src="51" dist="19" bctt="47" wctt="88"/>
    <tlink src="51" dist="20" bctt="39" wctt="41"/>
    <tlink src="51" dist="21" bctt="11" wctt="83"/>
    <tlink src="51" dist="22" bctt="19" wctt="60"/>
    <tlink src="51" dist="23" bctt="7" wctt="81"/>
    <tlink src="51" dist="24" bctt="15" wctt="44"/>
    <tlink src="52" dist="0" bctt="29" wctt="97"/>
    <tlink src="52" dist="1" bctt="60" wctt="83"/>
    <tlink src="52" dist="4" bctt="84" wctt="99"/>
    <tlink src="52" dist="5" bctt="7" wctt="10"/>
    <tlink src="52" dist="9" bctt="64" wctt="92"/>
    <tlink src="52" dist="11" bctt="97" wctt="97"/>
    <tlink src="52" dist="12" bctt="53" wctt="81"/>
    <tlink src="52" dist="13" bctt="4" wctt="69"/>
    <tlink src="52" dist="14" bctt="12" wctt="80"/>
    <tlink src="52" dist="15" bctt="0" wctt="2"/>
    <tlink src="52" dist="17" bctt="11" wctt="92"/>
    <tlink src="52" dist="18" bctt="9" wctt="17"/>
    <tlink src="52" dist="21" bctt="66" wctt="78"/>
    <tlink src="52" dist="22" bctt="0" wctt="4"/>
    <tlink src="52" dist="24" bctt="4" wctt="8"/>
    <tlink src="53" dist="2" bctt="39" wctt="50"/>
    <tlink src="53" dist="4" bctt="7" wctt="22"/>
    <tlink src="53" dist="5" bctt="22" wctt="79"/>
    <tlink src="53" dist="6" bctt="53" wctt="65"/>
    <tlink src="53" dist="9" bctt="3" wctt="45"/>
    <tlink src="53" dist="10" bctt="5" wctt="49"/>
    <tlink src="53" dist="13" bctt="9" wctt="21"/>
    <tlink src="53" dist="14" bctt="59" wctt="82"/>
    <tlink src="53" dist="15" bctt="43" wctt="94"/>
    <tlink src="53" dist="18" bctt="39" wctt="53"/>
    <tlink src="53" dist="19" bctt="62" wctt="81"/>
    <tlink src="53" dist="20" bctt="18" wctt="42"/>
    <tlink src="53" dist="22" bctt="45" wctt="45"/>
    <tlink src="53" dist="23" bctt="0" wctt="8"/>
    <tlink src="53" dist="24" bctt="12" wctt="44"/>
    <tlink src="54" dist="1" bctt="17" wctt="17"/>
    <tlink src="54" dist="2" bctt="44" wctt="70"/>
    <tlink src="54" dist="3" bctt="49" wctt="58"/>
    <tlink src="54" dist="4" bctt="24" wctt="90"/>
    <tlink src="54" dist="9" bctt="38" wctt="49"/>
    <tlink src="54" dist="10" bctt="74" wctt="91"/>
    <tlink src="54" dist="11" bctt="8" wctt="45"/>
    <tlink src="54" dist="13" bctt="23" wctt="49"/>
    <tlink src="54" dist="16" bctt="32" wctt="81"/>
    <tlink src="54" dist="17" bctt="4" wctt="11"/>
    <tlink src="54" dist="18" bctt="5" wctt="10"/>
    <tlink src="54" dist="19" bctt="46" wctt="58"/>
    <tlink src="54" dist="20" bctt="28" wctt="92"/>
    <tlink src="54" dist="23" bctt="6" wctt="11"/>
    <tlink src="55" dist="0" bctt="5" wctt="8"/>
    <tlink src="55" dist="4" bctt="2" wctt="53"/>
    <tlink src="55" dist="5" bctt="44" wctt="99"/>
    <tlink src="55" dist="7" bctt="12" wctt="28"/>
    <tlink src="55" dist="11" bctt="63" wctt="70"/>
    <tlink src="55" dist="12" bctt="65" wctt="91"/>
    <tlink src="55" dist="13" bctt="25" wctt="68"/>
    <tlink src="55" dist="14" bctt="20" wctt="29"/>
    <tlink src="55" dist="15" bctt="4" wctt="11"/>
    <tlink src="55" dist="18" bctt="6" wctt="6"/>
    <tlink src="55" dist="21" bctt="9" wctt="35"/>
    <tlink src="55" dist="22" bctt="7" wctt="22"/>
    <tlink src="55" dist="23" bctt="0" wctt="9"/>
    <tlink src="56" dist="0" bctt="3" wctt="6"/>
    <tlink src="56" dist="1" bctt="39" wctt="42"/>
    <tlink src="56" dist="2" bctt="44" wctt="56"/>
    <tlink src="56" dist="3" bctt="19" wctt="30"/>
    <tlink src="56" dist="5" bctt="30" wctt="34"/>
    <tlink src="56" dist="6" bctt="6" wctt="75"/>
    <tlink src="56" dist="7" bctt="4" wctt="45"/>
    <tlink src="56" dist="8" bctt="28" wctt="29"/>
    <tlink src="56" dist="10" bctt="37" wctt="69"/>
    <tlink src="56" dist="11" bctt="30" wctt="55"/>
    <tlink src="56" dist="12" bctt="24" wctt="47"/>
    <tlink src="56" dist="16" bctt="11" wctt="19"/>
    <tlink src="56" dist="17" bctt="14" wctt="62"/>
    <tlink src="56" dist="18" bctt="18" wctt="51"/>
    <tlink src="56" dist="19" bctt="9" wctt="53"/>
    <tlink src="56" dist="21" bctt="16" wctt="38"/>
    <tlink src="56" dist="23" bctt="9" wctt="59"/>
    <tlink src="56" dist="24" bctt="92" wctt="98"/>
    <tlink src="57" dist="0" bctt="34" wctt="44"/>
    <tlink src="57" dist="1" bctt="61" wctt="91"/>
    <tlink src="57" dist="5" bctt="1" wctt="2"/>
    <tlink src="57" dist="7" bctt="24" wctt="82"/>
    <tlink src="57" dist="8" bctt="13" wctt="75"/>
    <tlink src="57" dist="9" bctt="29" wctt="93"/>
    <tlink src="57" dist="10" bctt="5" wctt="27"/>
    <tlink src="57" dist="11" bctt="26" wctt="49"/>
    <tlink src="57" dist="12" bctt="2" wctt="82"/>
    <tlink src="57" dist="14" bctt="12" wctt="43"/>
    <tlink src="57" dist="15" bctt="19" wctt="26"/>
    <tlink src="57" dist="17" bctt="83" wctt="91"/>
    <tlink src="57" dist="20" bctt="6" wctt="10"/>
    <tlink src="57" dist="21" bctt="4" wctt="32"/>
    <tlink src="57" dist="22" bctt="0" wctt="19"/>
    <tlink src="57" dist="24" bctt="11" wctt="17"/>
    <tlink src="57" dist="63" bctt="33" wctt="80"/>
    <tlink src="58" dist="0" bctt="56" wctt="82"/>
    <tlink src="58" dist="1" bctt="21" wctt="70"/>
    <tlink src="58" dist="2" bctt="19" wctt="29"/>
    <tlink src="58" dist="4" bctt="79" wctt="79"/>
    <tlink src="58" dist="5" bctt="80" wctt="85"/>
    <tlink src="58" dist="6" bctt="27" wctt="40"/>
    <tlink src="58" dist="7" bctt="7" wctt="12"/>
    <tlink src="58" dist="8" bctt="42" wctt="98"/>
    <tlink src="58" dist="10" bctt="41" wctt="82"/>
    <tlink src="58" dist="12" bctt="4" wctt="10"/>
    <tlink src="58" dist="13" bctt="61" wctt="83"/>
    <tlink src="58" dist="17" bctt="1" wctt="1"/>
    <tlink src="58" dist="21" bctt="13" wctt="59"/>
    <tlink src="58" dist="22" bctt="10" wctt="11"/>
    <tlink src="59" dist="2" bctt="41" wctt="45"/>
    <tlink src="59" dist="5" bctt="42" wctt="87"/>
    <tlink src="59" dist="6" bctt="74" wctt="97"/>
    <tlink src="59" dist="9" bctt="1" wctt="1"/>
    <tlink src="59" dist="10" bctt="20" wctt="91"/>
    <tlink src="59" dist="11" bctt="1" wctt="28"/>
    <tlink src="59" dist="13" bctt="39" wctt="92"/>
    <tlink src="59" dist="15" bctt="3" wctt="6"/>
    <tlink src="59" dist="18" bctt="14" wctt="25"/>
    <tlink src="59" dist="23" bctt="53" wctt="94"/>
    <tlink src="59" dist="24" bctt="33" wctt="36"/>
    <tlink src="60" dist="0" bctt="33" wctt="51"/>
    <tlink src="60" dist="1" bctt="6" wctt="74"/>
    <tlink src="60" dist="2" bctt="73" wctt="96"/>
    <tlink src="60" dist="3" bctt="11" wctt="19"/>
    <tlink src="60" dist="4" bctt="48" wctt="52"/>
    <tlink src="60" dist="6" bctt="32" wctt="39"/>
    <tlink src="60" dist="7" bctt="16" wctt="75"/>
    <tlink src="60" dist="8" bctt="65" wctt="95"/>
    <tlink src="60" dist="10" bctt="41" wctt="57"/>
    <tlink src="60" dist="14" bctt="45" wctt="75"/>
    <tlink src="60" dist="15" bctt="18" wctt="19"/>
    <tlink src="60" dist="17" bctt="27" wctt="50"/>
    <tlink src="60" dist="19" bctt="4" wctt="12"/>
    <tlink src="60" dist="20" bctt="32" wctt="88"/>
    <tlink src="60" dist="21" bctt="29" wctt="99"/>
    <tlink src="60" dist="24" bctt="10" wctt="80"/>
    <tlink src="61" dist="4" bctt="18" wctt="19"/>
    <tlink src="61" dist="6" bctt="1" wctt="54"/>
    <tlink src="61" dist="11" bctt="14" wctt="29"/>
    <tlink src="61" dist="13" bctt="0" wctt="1"/>
    <tlink src="61" dist="14" bctt="26" wctt="51"/>
    <tlink src="61" dist="16" bctt="21" wctt="96"/>
    <tlink src="61" dist="17" bctt="27" wctt="34"/>
    <tlink src="61" dist="18" bctt="52" wctt="87"/>
    <tlink src="61" dist="19" bctt="8" wctt="10"/>
    <tlink src="61" dist="20" bctt="6" wctt="12"/>
    <tlink src="61" dist="21" bctt="3" wctt="8"/>
    <tlink src="62" dist="0" bctt="13" wctt="97"/>
    <tlink src="62" dist="1" bctt="30" wctt="77"/>
    <tlink src="62" dist="5" bctt="66" wctt="70"/>
    <tlink src="62" dist="7" bctt="15" wctt="30"/>
    <tlink src="62" dist="9" bctt="26" wctt="32"/>
    <tlink src="62" dist="11" bctt="64" wctt="89"/>
    <tlink src="62" dist="14" bctt="64" wctt="84"/>
    <tlink src="62" dist="16" bctt="4" wctt="29"/>
    <tlink src="62" dist="18" bctt="16" wctt="49"/>
    <tlink src="62" dist="19" bctt="8" wctt="31"/>
    <tlink src="62" dist="20" bctt="34" wctt="79"/>
    <tlink src="62" dist="23" bctt="68" wctt="96"/>
    <tlink src="62" dist="24" bctt="8" wctt="97"/>
    <tlink src="63" dist="1" bctt="15" wctt="85"/>
    <tlink src="63" dist="2" bctt="34" wctt="40"/>
    <tlink src="63" dist="3" bctt="1" wctt="5"/>
    <tlink src="63" dist="8" bctt="6" wctt="12"/>
    <tlink src="63" dist="9" bctt="37" wctt="53"/>
    <tlink src="63" dist="10" bctt="22" wctt="87"/>
    <tlink src="63" dist="11" bctt="7" wctt="41"/>
    <tlink src="63" dist="12" bctt="40" wctt="82"/>
    <tlink src="63" dist="14" bctt="17" wctt="60"/>
    <tlink src="63" dist="15" bctt="23" wctt="48"/>
    <tlink src="63" dist="17" bctt="2" wctt="36"/>
    <tlink src="63" dist="19" bctt="5" wctt="9"/>
    <tlink src="63" dist="20" bctt="27" wctt="47"/>
    <tlink src="63" dist="23" bctt="23" wctt="23"/>
    <tlink src="64" dist="0" bctt="19" wctt="21"/>
    <tlink src="64" dist="6" bctt="1" wctt="17"/>
    <tlink src="64" dist="7" bctt="1" wctt="1"/>
    <tlink src="64" dist="9" bctt="11" wctt="32"/>
    <tlink src="64" dist="10" bctt="33" wctt="37"/>
    <tlink src="64" dist="11" bctt="35" wctt="52"/>
    <tlink src="64" dist="13" bctt="52" wctt="53"/>
    <tlink src="64" dist="14" bctt="1" wctt="9"/>
    <tlink src="64" dist="18" bctt="21" wctt="27"/>
    <tlink src="64" dist="19" bctt="19" wctt="86"/>
    <tlink src="64" dist="21" bctt="18" wctt="54"/>
    <tlink src="64" dist="22" bctt="67" wctt="76"/>
    <tlink src="64" dist="23" bctt="10" wctt="10"/>
    <tlink src="65" dist="0" bctt="2" wctt="9"/>
    <tlink src="65" dist="1" bctt="15" wctt="45"/>
    <tlink src="65" dist="2" bctt="17" wctt="29"/>
    <tlink src="65" dist="5" bctt="16" wctt="25"/>
    <tlink src="65" dist="6" bctt="8" wctt="69"/>
    <tlink src="65" dist="7" bctt="39" wctt="70"/>
    <tlink src="65" dist="8" bctt="72" wctt="92"/>
    <tlink src="65" dist="9" bctt="1" wctt="45"/>
    <tlink src="65" dist="10" bctt="27" wctt="44"/>
    <tlink src="65" dist="11" bctt="57" wctt="57"/>
    <tlink src="65" dist="12" bctt="1" wctt="15"/>
    <tlink src="65" dist="13" bctt="19" wctt="72"/>
    <tlink src="65" dist="14" bctt="1" wctt="7"/>
    <tlink src="65" dist="15" bctt="80" wctt="92"/>
    <tlink src="65" dist="16" bctt="3" wctt="61"/>
    <tlink src="65" dist="17" bctt="12" wctt="14"/>
    <tlink src="65" dist="20" bctt="0" wctt="17"/>
    <tlink src="65" dist="21" bctt="50" wctt="65"/>
    <tlink src="65" dist="23" bctt="27" wctt="81"/>
    <tlink src="66" dist="0" bctt="6" wctt="21"/>
    <tlink src="66" dist="2" bctt="14" wctt="34"/>
    <tlink src="66" dist="3" bctt="30" wctt="32"/>
    <tlink src="66" dist="5" bctt="5" wctt="6"/>
    <tlink src="66" dist="6" bctt="26" wctt="42"/>
    <tlink src="66" dist="7" bctt="36" wctt="90"/>
    <tlink src="66" dist="9" bctt="56" wctt="66"/>
    <tlink src="66" dist="10" bctt="1" wctt="5"/>
    <tlink src="66" dist="11" bctt="3" wctt="68"/>
    <tlink src="66" dist="12" bctt="25" wctt="46"/>
    <tlink src="66" dist="14" bctt="9" wctt="51"/>
    <tlink src="66" dist="15" bctt="42" wctt="42"/>
    <tlink src="66" dist="16" bctt="57" wctt="61"/>
    <tlink src="66" dist="18" bctt="6" wctt="12"/>
    <tlink src="66" dist="21" bctt="9" wctt="17"/>
    <tlink src="66" dist="22" bctt="5" wctt="12"/>
    <tlink src="66" dist="24" bctt="72" wctt="84"/>
    <tlink src="67" dist="4" bctt="2" wctt="2"/>
    <tlink src="67" dist="5" bctt="11" wctt="21"/>
    <tlink src="67" dist="6" bctt="6" wctt="38"/>
    <tlink src="67" dist="8" bctt="3" wctt="36"/>
    <tlink src="67" dist="9" bctt="12" wctt="12"/>
    <tlink src="67" dist="10" bctt="3" wctt="23"/>
    <tlink src="67" dist="12" bctt="19" wctt="32"/>
    <tlink src="67" dist="13" bctt="42" wctt="74"/>
    <tlink src="67" dist="14" bctt="9" wctt="51"/>
    <tlink src="67" dist="15" bctt="40" wctt="100"/>
    <tlink src="67" dist="17" bctt="0" wctt="41"/>
    <tlink src="67" dist="18" bctt="13" wctt="20"/>
    <tlink src="67" dist="19" bctt="29" wctt="59"/>
    <tlink src="67" dist="20" bctt="22" wctt="27"/>
    <tlink src="67" dist="21" bctt="38" wctt="97"/>
    <tlink src="67" dist="22" bctt="2" wctt="10"/>
    <tlink src="67" dist="23" bctt="79" wctt="96"/>
    <tlink src="67" dist="24" bctt="73" wctt="84"/>
    <tlink src="68" dist="1" bctt="40" wctt="40"/>
    <tlink src="68" dist="2" bctt="33" wctt="76"/>
    <tlink src="68" dist="3" bctt="6" wctt="83"/>
    <tlink src="68" dist="8" bctt="18" wctt="29"/>
    <tlink src="68" dist="9" bctt="23" wctt="67"/>
    <tlink src="68" dist="10" bctt="29" wctt="29"/>
    <tlink src="68" dist="11" bctt="10" wctt="19"/>
    <tlink src="68" dist="12" bctt="17" wctt="22"/>
    <tlink src="68" dist="15" bctt="80" wctt="85"/>
    <tlink src="68" dist="17" bctt="1" wctt="2"/>
    <tlink src="68" dist="20" bctt="31" wctt="62"/>
    <tlink src="68" dist="22" bctt="8" wctt="95"/>
    <tlink src="69" dist="1" bctt="6" wctt="15"/>
    <tlink src="69" dist="2" bctt="73" wctt="99"/>
    <tlink src="69" dist="5" bctt="21" wctt="46"/>
    <tlink src="69" dist="6" bctt="16" wctt="63"/>
    <tlink src="69" dist="7" bctt="18" wctt="32"/>
    <tlink src="69" dist="8" bctt="97" wctt="98"/>
    <tlink src="69" dist="9" bctt="88" wctt="94"/>
    <tlink src="69" dist="10" bctt="88" wctt="90"/>
    <tlink src="69" dist="12" bctt="31" wctt="85"/>
    <tlink src="69" dist="13" bctt="15" wctt="19"/>
    <tlink src="69" dist="14" bctt="54" wctt="55"/>
    <tlink src="69" dist="15" bctt="47" wctt="79"/>
    <tlink src="69" dist="18" bctt="6" wctt="15"/>
    <tlink src="69" dist="19" bctt="47" wctt="69"/>
    <tlink src="69" dist="22" bctt="62" wctt="86"/>
    <tlink src="69" dist="23" bctt="11" wctt="42"/>
    <tlink src="70" dist="1" bctt="1" wctt="43"/>
    <tlink src="70" dist="2" bctt="11" wctt="64"/>
    <tlink src="70" dist="3" bctt="5" wctt="32"/>
    <tlink src="70" dist="4" bctt="10" wctt="58"/>
    <tlink src="70" dist="6" bctt="2" wctt="18"/>
    <tlink src="70" dist="7" bctt="13" wctt="34"/>
    <tlink src="70" dist="14" bctt="70" wctt="73"/>
    <tlink src="70" dist="18" bctt="1" wctt="9"/>
    <tlink src="70" dist="19" bctt="24" wctt="29"/>
    <tlink src="70" dist="21" bctt="11" wctt="24"/>
    <tlink src="70" dist="22" bctt="30" wctt="48"/>
    <tlink src="70" dist="23" bctt="5" wctt="20"/>
    <tlink src="70" dist="24" bctt="34" wctt="34"/>
    <tlink src="71" dist="0" bctt="28" wctt="87"/>
    <tlink src="71" dist="2" bctt="0" wctt="96"/>
    <tlink src="71" dist="5" bctt="8" wctt="51"/>
    <tlink src="71" dist="6" bctt="0" wctt="1"/>
    <tlink src="71" dist="9" bctt="30" wctt="44"/>
    <tlink src="71" dist="10" bctt="24" wctt="76"/>
    <tlink src="71" dist="12" bctt="19" wctt="88"/>
    <tlink src="71" dist="14" bctt="24" wctt="31"/>
    <tlink src="71" dist="15" bctt="4" wctt="28"/>
    <tlink src="71" dist="17" bctt="10" wctt="11"/>
    <tlink src="71" dist="18" bctt="0" wctt="4"/>
    <tlink src="71" dist="19" bctt="10" wctt="43"/>
    <tlink src="71" dist="21" bctt="16" wctt="50"/>
    <tlink src="71" dist="23" bctt="12" wctt="49"/>
    <tlink src="72" dist="1" bctt="18" wctt="29"/>
    <tlink src="72" dist="2" bctt="5" wctt="6"/>
    <tlink src="72" dist="5" bctt="5" wctt="51"/>
    <tlink src="72" dist="8" bctt="95" wctt="95"/>
    <tlink src="72" dist="11" bctt="0" wctt="55"/>
    <tlink src="72" dist="12" bctt="5" wctt="30"/>
    <tlink src="72" dist="13" bctt="43" wctt="47"/>
    <tlink src="72" dist="16" bctt="10" wctt="81"/>
    <tlink src="72" dist="18" bctt="83" wctt="85"/>
    <tlink src="72" dist="20" bctt="55" wctt="62"/>
    <tlink src="72" dist="22" bctt="53" wctt="85"/>
    <tlink src="72" dist="23" bctt="40" wctt="45"/>
    <tlink src="72" dist="24" bctt="9" wctt="25"/>
    <tlink src="73" dist="2" bctt="6" wctt="34"/>
    <tlink src="73" dist="3" bctt="26" wctt="62"/>
    <tlink src="73" dist="5" bctt="3" wctt="32"/>
    <tlink src="73" dist="6" bctt="66" wctt="95"/>
    <tlink src="73" dist="11" bctt="55" wctt="62"/>
    <tlink src="73" dist="12" bctt="4" wctt="18"/>
    <tlink src="73" dist="13" bctt="33" wctt="43"/>
    <tlink src="73" dist="18" bctt="38" wctt="51"/>
    <tlink src="73" dist="19" bctt="22" wctt="25"/>
    <tlink src="73" dist="21" bctt="3" wctt="21"/>
    <tlink src="73" dist="24" bctt="44" wctt="57"/>
    <tlink src="74" dist="1" bctt="3" wctt="4"/>
    <tlink src="74" dist="2" bctt="7" wctt="8"/>
    <tlink src="74" dist="3" bctt="4" wctt="52"/>
    <tlink src="74" dist="6" bctt="24" wctt="95"/>
    <tlink src="74" dist="7" bctt="53" wctt="85"/>
    <tlink src="74" dist="10" bctt="18" wctt="23"/>
    <tlink src="74" dist="11" bctt="0" wctt="42"/>
    <tlink src="74" dist="12" bctt="0" wctt="28"/>
    <tlink src="74" dist="13" bctt="36" wctt="40"/>
    <tlink src="74" dist="14" bctt="8" wctt="97"/>
    <tlink src="74" dist="16" bctt="5" wctt="5"/>
    <tlink src="74" dist="17" bctt="28" wctt="94"/>
    <tlink src="74" dist="19" bctt="40" wctt="64"/>
    <tlink src="74" dist="20" bctt="17" wctt="29"/>
    <tlink src="74" dist="21" bctt="2" wctt="3"/>
    <tlink src="74" dist="22" bctt="37" wctt="51"/>
    <tlink src="74" dist="23" bctt="21" wctt="55"/>
    <tlink src="75" dist="2" bctt="46" wctt="72"/>
    <tlink src="75" dist="3" bctt="2" wctt="14"/>
    <tlink src="75" dist="4" bctt="15" wctt="31"/>
    <tlink src="75" dist="5" bctt="68" wctt="78"/>
    <tlink src="75" dist="7" bctt="7" wctt="51"/>
    <tlink src="75" dist="15" bctt="52" wctt="94"/>
    <tlink src="75" dist="17" bctt="12" wctt="13"/>
    <tlink src="75" dist="18" bctt="3" wctt="55"/>
    <tlink src="75" dist="20" bctt="52" wctt="71"/>
    <tlink src="75" dist="22" bctt="16" wctt="24"/>
    <tlink src="75" dist="23" bctt="57" wctt="74"/>
    <tlink src="75" dist="24" bctt="23" wctt="47"/>
    <tlink src="76" dist="0" bctt="55" wctt="82"/>
    <tlink src="76" dist="1" bctt="43" wctt="76"/>
    <tlink src="76" dist="2" bctt="12" wctt="75"/>
    <tlink src="76" dist="3" bctt="62" wctt="70"/>
    <tlink src="76" dist="7" bctt="2" wctt="27"/>
    <tlink src="76" dist="8" bctt="46" wctt="61"/>
    <tlink src="76" dist="9" bctt="2" wctt="3"/>
    <tlink src="76" dist="10" bctt="71" wctt="80"/>
    <tlink src="76" dist="12" bctt="11" wctt="20"/>
    <tlink src="76" dist="14" bctt="31" wctt="89"/>
    <tlink src="76" dist="15" bctt="48" wctt="66"/>
    <tlink src="76" dist="16" bctt="32" wctt="37"/>
    <tlink src="76" dist="20" bctt="27" wctt="61"/>
    <tlink src="76" dist="24" bctt="24" wctt="28"/>
    <tlink src="77" dist="1" bctt="0" wctt="1"/>
    <tlink src="77" dist="3" bctt="54" wctt="55"/>
    <tlink src="77" dist="4" bctt="66" wctt="73"/>
    <tlink src="77" dist="5" bctt="13" wctt="50"/>
    <tlink src="77" dist="8" bctt="8" wctt="28"/>
    <tlink src="77" dist="9" bctt="10" wctt="21"/>
    <tlink src="77" dist="10" bctt="18" wctt="52"/>
    <tlink src="77" dist="11" bctt="17" wctt="27"/>
    <tlink src="77" dist="13" bctt="57" wctt="91"/>
    <tlink src="77" dist="15" bctt="38" wctt="85"/>
    <tlink src="77" dist="16" bctt="20" wctt="71"/>
    <tlink src="77" dist="17" bctt="8" wctt="49"/>
    <tlink src="77" dist="18" bctt="80" wctt="84"/>
    <tlink src="77" dist="19" bctt="18" wctt="32"/>
    <tlink src="77" dist="20" bctt="10" wctt="56"/>
    <tlink src="77" dist="22" bctt="0" wctt="64"/>
    <tlink src="77" dist="24" bctt="14" wctt="18"/>
    <tlink src="78" dist="1" bctt="29" wctt="59"/>
    <tlink src="78" dist="3" bctt="4" wctt="47"/>
    <tlink src="78" dist="4" bctt="2" wctt="38"/>
    <tlink src="78" dist="5" bctt="53" wctt="57"/>
    <tlink src="78" dist="6" bctt="59" wctt="86"/>
    <tlink src="78" dist="7" bctt="8" wctt="8"/>
    <tlink src="78" dist="8" bctt="66" wctt="73"/>
    <tlink src="78" dist="9" bctt="35" wctt="52"/>
    <tlink src="78" dist="11" bctt="9" wctt="37"/>
    <tlink src="78" dist="12" bctt="53" wctt="55"/>
    <tlink src="78" dist="16" bctt="37" wctt="37"/>
    <tlink src="78" dist="18" bctt="28" wctt="31"/>
    <tlink src="78" dist="19" bctt="2" wctt="10"/>
    <tlink src="78" dist="21" bctt="88" wctt="98"/>
    <tlink src="78" dist="23" bctt="5" wctt="26"/>
    <tlink src="78" dist="24" bctt="16" wctt="53"/>
    <tlink src="79" dist="0" bctt="1" wctt="1"/>
    <tlink src="79" dist="1" bctt="9" wctt="27"/>
    <tlink src="79" dist="2" bctt="57" wctt="88"/>
    <tlink src="79" dist="4" bctt="54" wctt="56"/>
    <tlink src="79" dist="6" bctt="20" wctt="49"/>
    <tlink src="79" dist="7" bctt="27" wctt="100"/>
    <tlink src="79" dist="9" bctt="59" wctt="81"/>
    <tlink src="79" dist="10" bctt="41" wctt="56"/>
    <tlink src="79" dist="12" bctt="45" wctt="61"/>
    <tlink src="79" dist="13" bctt="0" wctt="10"/>
    <tlink src="79" dist="15" bctt="32" wctt="74"/>
    <tlink src="79" dist="17" bctt="36" wctt="100"/>
    <tlink src="79" dist="20" bctt="46" wctt="57"/>
    <tlink src="79" dist="21" bctt="8" wctt="46"/>
    <tlink src="79" dist="22" bctt="6" wctt="72"/>
    <tlink src="80" dist="2" bctt="15" wctt="27"/>
    <tlink src="80" dist="5" bctt="43" wctt="58"/>
    <tlink src="80" dist="6" bctt="26" wctt="28"/>
    <tlink src="80" dist="9" bctt="55" wctt="59"/>
    <tlink src="80" dist="10" bctt="89" wctt="97"/>
    <tlink src="80" dist="11" bctt="0" wctt="4"/>
    <tlink src="80" dist="12" bctt="18" wctt="18"/>
    <tlink src="80" dist="15" bctt="2" wctt="66"/>
    <tlink src="80" dist="19" bctt="10" wctt="17"/>
    <tlink src="80" dist="20" bctt="38" wctt="46"/>
    <tlink src="80" dist="21" bctt="8" wctt="24"/>
    <tlink src="80" dist="22" bctt="3" wctt="9"/>
    <tlink src="80" dist="23" bctt="18" wctt="36"/>
    <tlink src="81" dist="3" bctt="33" wctt="54"/>
    <tlink src="81" dist="6" bctt="12" wctt="14"/>
    <tlink src="81" dist="7" bctt="35" wctt="35"/>
    <tlink src="81" dist="9" bctt="27" wctt="40"/>
    <tlink src="81" dist="10" bctt="46" wctt="71"/>
    <tlink src="81" dist="11" bctt="2" wctt="9"/>
    <tlink src="81" dist="12" bctt="6" wctt="70"/>
    <tlink src="81" dist="13" bctt="10" wctt="74"/>
    <tlink src="81" dist="16" bctt="11" wctt="91"/>
    <tlink src="81" dist="17" bctt="16" wctt="26"/>
    <tlink src="81" dist="18" bctt="33" wctt="68"/>
    <tlink src="81" dist="19" bctt="18" wctt="18"/>
    <tlink src="81" dist="20" bctt="13" wctt="34"/>
    <tlink src="81" dist="21" bctt="49" wctt="59"/>
    <tlink src="81" dist="23" bctt="1" wctt="40"/>
    <tlink src="82" dist="0" bctt="33" wctt="77"/>
    <tlink src="82" dist="1" bctt="3" wctt="64"/>
    <tlink src="82" dist="4" bctt="18" wctt="38"/>
    <tlink src="82" dist="6" bctt="31" wctt="54"/>
    <tlink src="82" dist="7" bctt="28" wctt="88"/>
    <tlink src="82" dist="8" bctt="6" wctt="25"/>
    <tlink src="82" dist="11" bctt="23" wctt="88"/>
    <tlink src="82" dist="14" bctt="0" wctt="14"/>
    <tlink src="82" dist="16" bctt="1" wctt="39"/>
    <tlink src="82" dist="18" bctt="39" wctt="54"/>
    <tlink src="82" dist="20" bctt="53" wctt="58"/>
    <tlink src="82" dist="22" bctt="72" wctt="87"/>
    <tlink src="82" dist="24" bctt="5" wctt="11"/>
    <tlink src="83" dist="1" bctt="63" wctt="97"/>
    <tlink src="83" dist="2" bctt="1" wctt="18"/>
    <tlink src="83" dist="3" bctt="15" wctt="69"/>
    <tlink src="83" dist="4" bctt="4" wctt="34"/>
    <tlink src="83" dist="7" bctt="6" wctt="66"/>
    <tlink src="83" dist="8" bctt="16" wctt="59"/>
    <tlink src="83" dist="9" bctt="28" wctt="57"/>
    <tlink src="83" dist="10" bctt="72" wctt="89"/>
    <tlink src="83" dist="13" bctt="8" wctt="87"/>
    <tlink src="83" dist="17" bctt="78" wctt="87"/>
    <tlink src="83" dist="18" bctt="26" wctt="37"/>
    <tlink src="83" dist="20" bctt="14" wctt="69"/>
    <tlink src="83" dist="23" bctt="5" wctt="13"/>
    <tlink src="84" dist="1" bctt="25" wctt="30"/>
    <tlink src="84" dist="3" bctt="49" wctt="97"/>
    <tlink src="84" dist="6" bctt="33" wctt="84"/>
    <tlink src="84" dist="8" bctt="24" wctt="71"/>
    <tlink src="84" dist="9" bctt="48" wctt="48"/>
    <tlink src="84" dist="10" bctt="26" wctt="32"/>
    <tlink src="84" dist="12" bctt="36" wctt="66"/>
    <tlink src="84" dist="13" bctt="31" wctt="53"/>
    <tlink src="84" dist="16" bctt="7" wctt="11"/>
    <tlink src="84" dist="17" bctt="21" wctt="55"/>
    <tlink src="84" dist="19" bctt="0" wctt="1"/>
    <tlink src="84" dist="20" bctt="12" wctt="35"/>
    <tlink src="84" dist="21" bctt="3" wctt="3"/>
    <tlink src="84" dist="22" bctt="70" wctt="86"/>
    <tlink src="84" dist="23" bctt="13" wctt="55"/>
    <tlink src="84" dist="24" bctt="12" wctt="34"/>
    <tlink src="85" dist="1" bctt="53" wctt="100"/>
    <tlink src="85" dist="3" bctt="18" wctt="47"/>
    <tlink src="85" dist="4" bctt="38" wctt="68"/>
    <tlink src="85" dist="6" bctt="88" wctt="97"/>
    <tlink src="85" dist="8" bctt="5" wctt="41"/>
    <tlink src="85" dist="9" bctt="68" wctt="93"/>
    <tlink src="85" dist="12" bctt="48" wctt="95"/>
    <tlink src="85" dist="14" bctt="41" wctt="96"/>
    <tlink src="85" dist="17" bctt="5" wctt="36"/>
    <tlink src="85" dist="18" bctt="6" wctt="26"/>
    <tlink src="85" dist="22" bctt="36" wctt="60"/>
    <tlink src="85" dist="23" bctt="20" wctt="67"/>
    <tlink src="85" dist="24" bctt="46" wctt="47"/>
    <tlink src="86" dist="0" bctt="9" wctt="37"/>
    <tlink src="86" dist="1" bctt="31" wctt="65"/>
    <tlink src="86" dist="3" bctt="13" wctt="14"/>
    <tlink src="86" dist="4" bctt="61" wctt="68"/>
    <tlink src="86" dist="5" bctt="21" wctt="70"/>
    <tlink src="86" dist="6" bctt="0" wctt="5"/>
    <tlink src="86" dist="8" bctt="8" wctt="22"/>
    <tlink src="86" dist="9" bctt="9" wctt="38"/>
    <tlink src="86" dist="10" bctt="5" wctt="96"/>
    <tlink src="86" dist="11" bctt="56" wctt="67"/>
    <tlink src="86" dist="12" bctt="25" wctt="66"/>
    <tlink src="86" dist="13" bctt="28" wctt="62"/>
    <tlink src="86" dist="14" bctt="19" wctt="55"/>
    <tlink src="86" dist="18" bctt="15" wctt="52"/>
    <tlink src="86" dist="19" bctt="23" wctt="45"/>
    <tlink src="86" dist="21" bctt="41" wctt="85"/>
    <tlink src="86" dist="22" bctt="14" wctt="43"/>
    <tlink src="87" dist="0" bctt="0" wctt="1"/>
    <tlink src="87" dist="2" bctt="16" wctt="18"/>
    <tlink src="87" dist="3" bctt="41" wctt="79"/>
    <tlink src="87" dist="4" bctt="0" wctt="2"/>
    <tlink src="87" dist="6" bctt="2" wctt="4"/>
    <tlink src="87" dist="8" bctt="7" wctt="15"/>
    <tlink src="87" dist="10" bctt="19" wctt="22"/>
    <tlink src="87" dist="11" bctt="20" wctt="45"/>
    <tlink src="87" dist="12" bctt="7" wctt="67"/>
    <tlink src="87" dist="13" bctt="3" wctt="14"/>
    <tlink src="87" dist="17" bctt="18" wctt="26"/>
    <tlink src="87" dist="18" bctt="17" wctt="53"/>
    <tlink src="87" dist="22" bctt="22" wctt="24"/>
    <tlink src="87" dist="23" bctt="4" wctt="8"/>
    <tlink src="88" dist="0" bctt="7" wctt="76"/>
    <tlink src="88" dist="5" bctt="1" wctt="54"/>
    <tlink src="88" dist="6" bctt="49" wctt="99"/>
    <tlink src="88" dist="7" bctt="56" wctt="61"/>
    <tlink src="88" dist="8" bctt="43" wctt="57"/>
    <tlink src="88" dist="11" bctt="63" wctt="84"/>
    <tlink src="88" dist="12" bctt="7" wctt="13"/>
    <tlink src="88" dist="16" bctt="7" wctt="42"/>
    <tlink src="88" dist="18" bctt="3" wctt="17"/>
    <tlink src="88" dist="19" bctt="27" wctt="66"/>
    <tlink src="88" dist="21" bctt="12" wctt="21"/>
    <tlink src="88" dist="22" bctt="97" wctt="99"/>
    <tlink src="89" dist="1" bctt="11" wctt="20"/>
    <tlink src="89" dist="2" bctt="33" wctt="37"/>
    <tlink src="89" dist="4" bctt="8" wctt="15"/>
    <tlink src="89" dist="5" bctt="56" wctt="80"/>
    <tlink src="89" dist="6" bctt="58" wctt="91"/>
    <tlink src="89" dist="7" bctt="7" wctt="42"/>
    <tlink src="89" dist="8" bctt="57" wctt="73"/>
    <tlink src="89" dist="9" bctt="12" wctt="27"/>
    <tlink src="89" dist="14" bctt="19" wctt="59"/>
    <tlink src="89" dist="15" bctt="40" wctt="72"/>
    <tlink src="89" dist="16" bctt="0" wctt="15"/>
    <tlink src="89" dist="20" bctt="3" wctt="6"/>
    <tlink src="89" dist="21" bctt="58" wctt="75"/>
    <tlink src="89" dist="22" bctt="2" wctt="33"/>
    <tlink src="89" dist="24" bctt="15" wctt="37"/>
    <tlink src="90" dist="9" bctt="7" wctt="15"/>
    <tlink src="90" dist="10" bctt="28" wctt="41"/>
    <tlink src="90" dist="12" bctt="1" wctt="18"/>
    <tlink src="90" dist="14" bctt="17" wctt="73"/>
    <tlink src="90" dist="16" bctt="24" wctt="27"/>
    <tlink src="90" dist="17" bctt="9" wctt="12"/>
    <tlink src="90" dist="19" bctt="64" wctt="72"/>
    <tlink src="90" dist="20" bctt="69" wctt="94"/>
    <tlink src="90" dist="21" bctt="32" wctt="39"/>
    <tlink src="91" dist="3" bctt="7" wctt="14"/>
    <tlink src="91" dist="4" bctt="9" wctt="23"/>
    <tlink src="91" dist="7" bctt="13" wctt="69"/>
    <tlink src="91" dist="8" bctt="24" wctt="26"/>
    <tlink src="91" dist="15" bctt="39" wctt="98"/>
    <tlink src="91" dist="16" bctt="29" wctt="89"/>
    <tlink src="91" dist="17" bctt="12" wctt="18"/>
    <tlink src="91" dist="19" bctt="2" wctt="5"/>
    <tlink src="91" dist="20" bctt="6" wctt="50"/>
    <tlink src="91" dist="21" bctt="31" wctt="84"/>
    <tlink src="92" dist="0" bctt="43" wctt="49"/>
    <tlink src="92" dist="1" bctt="2" wctt="10"/>
    <tlink src="92" dist="4" bctt="1" wctt="12"/>
    <tlink src="92" dist="6" bctt="0" wctt="24"/>
    <tlink src="92" dist="7" bctt="67" wctt="86"/>
    <tlink src="92" dist="9" bctt="28" wctt="67"/>
    <tlink src="92" dist="10" bctt="18" wctt="18"/>
    <tlink src="92" dist="11" bctt="20" wctt="34"/>
    <tlink src="92" dist="13" bctt="50" wctt="65"/>
    <tlink src="92" dist="14" bctt="24" wctt="77"/>
    <tlink src="92" dist="15" bctt="32" wctt="38"/>
    <tlink src="92" dist="19" bctt="33" wctt="75"/>
    <tlink src="92" dist="21" bctt="5" wctt="15"/>
    <tlink src="92" dist="22" bctt="44" wctt="47"/>
    <tlink src="92" dist="23" bctt="11" wctt="97"/>
    <tlink src="93" dist="1" bctt="8" wctt="27"/>
    <tlink src="93" dist="2" bctt="46" wctt="85"/>
    <tlink src="93" dist="6" bctt="8" wctt="43"/>
    <tlink src="93" dist="7" bctt="4" wctt="14"/>
    <tlink src="93" dist="8" bctt="45" wctt="53"/>
    <tlink src="93" dist="9" bctt="35" wctt="87"/>
    <tlink src="93" dist="10" bctt="41" wctt="46"/>
    <tlink src="93" dist="12" bctt="15" wctt="83"/>
    <tlink src="93" dist="13" bctt="34" wctt="92"/>
    <tlink src="93" dist="16" bctt="43" wctt="48"/>
    <tlink src="93" dist="17" bctt="69" wctt="98"/>
    <tlink src="93" dist="21" bctt="86" wctt="88"/>
    <tlink src="93" dist="22" bctt="7" wctt="14"/>
    <tlink src="94" dist="1" bctt="63" wctt="91"/>
    <tlink src="94" dist="2" bctt="0" wctt="16"/>
    <tlink src="94" dist="3" bctt="10" wctt="31"/>
    <tlink src="94" dist="4" bctt="2" wctt="11"/>
    <tlink src="94" dist="6" bctt="42" wctt="73"/>
    <tlink src="94" dist="7" bctt="24" wctt="99"/>
    <tlink src="94" dist="8" bctt="38" wctt="44"/>
    <tlink src="94" dist="9" bctt="16" wctt="29"/>
    <tlink src="94" dist="10" bctt="7" wctt="14"/>
    <tlink src="94" dist="11" bctt="0" wctt="1"/>
    <tlink src="94" dist="13" bctt="35" wctt="53"/>
    <tlink src="94" dist="14" bctt="36" wctt="62"/>
    <tlink src="94" dist="15" bctt="12" wctt="29"/>
    <tlink src="94" dist="16" bctt="2" wctt="20"/>
    <tlink src="94" dist="18" bctt="14" wctt="39"/>
    <tlink src="94" dist="19" bctt="7" wctt="74"/>
    <tlink src="94" dist="20" bctt="5" wctt="64"/>
    <tlink src="94" dist="21" bctt="17" wctt="37"/>
    <tlink src="94" dist="22" bctt="0" wctt="4"/>
    <tlink src="95" dist="2" bctt="50" wctt="86"/>
    <tlink src="95" dist="4" bctt="54" wctt="70"/>
    <tlink src="95" dist="5" bctt="39" wctt="93"/>
    <tlink src="95" dist="6" bctt="2" wctt="2"/>
    <tlink src="95" dist="9" bctt="27" wctt="82"/>
    <tlink src="95" dist="10" bctt="67" wctt="83"/>
    <tlink src="95" dist="11" bctt="23" wctt="53"/>
    <tlink src="95" dist="12" bctt="63" wctt="65"/>
    <tlink src="95" dist="14" bctt="68" wctt="69"/>
    <tlink src="95" dist="15" bctt="60" wctt="60"/>
    <tlink src="95" dist="16" bctt="12" wctt="40"/>
    <tlink src="95" dist="18" bctt="1" wctt="3"/>
    <tlink src="95" dist="20" bctt="29" wctt="78"/>
    <tlink src="95" dist="22" bctt="20" wctt="47"/>
    <tlink src="95" dist="23" bctt="12" wctt="12"/>
    <tlink src="95" dist="24" bctt="65" wctt="84"/>
    <tlink src="96" dist="0" bctt="74" wctt="79"/>
    <tlink src="96" dist="1" bctt="7" wctt="23"/>
    <tlink src="96" dist="2" bctt="0" wctt="4"/>
    <tlink src="96" dist="5" bctt="17" wctt="42"/>
    <tlink src="96" dist="6" bctt="33" wctt="57"/>
    <tlink src="96" dist="7" bctt="8" wctt="49"/>
    <tlink src="96" dist="9" bctt="72" wctt="84"/>
    <tlink src="96" dist="10" bctt="24" wctt="60"/>
    <tlink src="96" dist="11" bctt="17" wctt="23"/>
    <tlink src="96" dist="13" bctt="47" wctt="73"/>
    <tlink src="96" dist="17" bctt="12" wctt="18"/>
    <tlink src="96" dist="18" bctt="32" wctt="53"/>
    <tlink src="96" dist="19" bctt="18" wctt="20"/>
    <tlink src="96" dist="20" bctt="61" wctt="72"/>
    <tlink src="96" dist="21" bctt="4" wctt="86"/>
    <tlink src="96" dist="23" bctt="69" wctt="97"/>
    <tlink src="96" dist="24" bctt="38" wctt="91"/>
    <tlink src="97" dist="1" bctt="17" wctt="48"/>
    <tlink src="97" dist="2" bctt="6" wctt="10"/>
    <tlink src="97" dist="3" bctt="14" wctt="87"/>
    <tlink src="97" dist="4" bctt="6" wctt="43"/>
    <tlink src="97" dist="5" bctt="10" wctt="16"/>
    <tlink src="97" dist="6" bctt="38" wctt="89"/>
    <tlink src="97" dist="8" bctt="24" wctt="45"/>
    <tlink src="97" dist="11" bctt="7" wctt="15"/>
    <tlink src="97" dist="16" bctt="13" wctt="26"/>
    <tlink src="97" dist="19" bctt="0" wctt="4"/>
    <tlink src="97" dist="20" bctt="0" wctt="4"/>
    <tlink src="97" dist="21" bctt="9" wctt="11"/>
    <tlink src="97" dist="22" bctt="15" wctt="16"/>
    <tlink src="97" dist="23" bctt="13" wctt="26"/>
    <tlink src="97" dist="24" bctt="30" wctt="45"/>
    <tlink src="98" dist="1" bctt="4" wctt="11"/>
    <tlink src="98" dist="2" bctt="9" wctt="27"/>
    <tlink src="98" dist="3" bctt="45" wctt="79"/>
    <tlink src="98" dist="5" bctt="0" wctt="70"/>
    <tlink src="98" dist="8" bctt="1" wctt="3"/>
    <tlink src="98" dist="10" bctt="13" wctt="14"/>
    <tlink src="98" dist="11" bctt="2" wctt="70"/>
    <tlink src="98" dist="12" bctt="1" wctt="2"/>
    <tlink src="98" dist="13" bctt="21" wctt="66"/>
    <tlink src="98" dist="14" bctt="54" wctt="78"/>
    <tlink src="98" dist="15" bctt="28" wctt="56"/>
    <tlink src="98" dist="16" bctt="39" wctt="73"/>
    <tlink src="98" dist="17" bctt="4" wctt="56"/>
    <tlink src="98" dist="19" bctt="12" wctt="71"/>
    <tlink src="98" dist="20" bctt="29" wctt="35"/>
    <tlink src="98" dist="24" bctt="73" wctt="93"/>
    <tlink src="99" dist="0" bctt="6" wctt="16"/>
    <tlink src="99" dist="2" bctt="46" wctt="57"/>
    <tlink src="99" dist="3" bctt="48" wctt="73"/>
    <tlink src="99" dist="4" bctt="19" wctt="38"/>
    <tlink src="99" dist="7" bctt="7" wctt="24"/>
    <tlink src="99" dist="8" bctt="9" wctt="20"/>
    <tlink src="99" dist="9" bctt="43" wctt="76"/>
    <tlink src="99" dist="10" bctt="86" wctt="91"/>
    <tlink src="99" dist="11" bctt="1" wctt="28"/>
    <tlink src="99" dist="12" bctt="22" wctt="75"/>
    <tlink src="99" dist="13" bctt="50" wctt="73"/>
    <tlink src="99" dist="14" bctt="0" wctt="3"/>
    <tlink src="99" dist="16" bctt="40" wctt="48"/>
    <tlink src="99" dist="17" bctt="16" wctt="37"/>
    <tlink src="99" dist="18" bctt="7" wctt="7"/>
    <tlink src="99" dist="22" bctt="5" wctt="24"/>
    <tlink src="99" dist="23" bctt="19" wctt="60"/>
    <tlink src="100" dist="0" bctt="51" wctt="65"/>
    <tlink src="100" dist="2" bctt="25" wctt="79"/>
    <tlink src="100" dist="3" bctt="2" wctt="48"/>
    <tlink src="100" dist="5" bctt="5" wctt="12"/>
    <tlink src="100" dist="8" bctt="12" wctt="60"/>
    <tlink src="100" dist="9" bctt="19" wctt="33"/>
    <tlink src="100" dist="11" bctt="20" wctt="76"/>
    <tlink src="100" dist="12" bctt="19" wctt="75"/>
    <tlink src="100" dist="13" bctt="12" wctt="20"/>
    <tlink src="100" dist="14" bctt="1" wctt="8"/>
    <tlink src="100" dist="18" bctt="85" wctt="94"/>
    <tlink src="100" dist="20" bctt="68" wctt="79"/>
    <tlink src="100" dist="23" bctt="63" wctt="83"/>
</system>
